{
    "logo": {
        "url": "/images/logo-dark.svg",
        "altText": "Logo dark",
        "styles": {
            "self": {
                "margin": [
                    "mr-3"
                ]
            }
        },
        "type": "ImageBlock"
    },
    "primaryLinks": [
        {
            "label": "Blog",
            "altText": "Blog",
            "url": "/blog",
            "icon": "arrowRight",
            "iconPosition": "right",
            "style": "secondary",
            "type": "Link"
        },
        {
            "label": "My Networks",
            "altText": "Dropdown",
            "links": [
                {
                    "type": "Link",
                    "altText": "GitHub",
                    "url": "https://github.com/wealthcodednacode",
                    "showIcon": true,
                    "icon": "github",
                    "iconPosition": "left",
                    "style": "secondary",
                    "elementId": "",
                    "label": "Git Hub"
                },
                {
                    "type": "Link",
                    "altText": "Facebook",
                    "url": "https://www.facebook.com/WealthCode.DnaCode",
                    "showIcon": true,
                    "icon": "facebook",
                    "iconPosition": "left",
                    "style": "secondary",
                    "elementId": "",
                    "label": "Fan Page"
                },
                {
                    "type": "Link",
                    "label": "Instagram",
                    "altText": "Instagram",
                    "url": "https://www.instagram.com/daphongsila",
                    "showIcon": true,
                    "icon": "instagram",
                    "iconPosition": "left",
                    "style": "secondary",
                    "elementId": ""
                },
                {
                    "type": "Link",
                    "label": "Twitter",
                    "altText": "Twitter",
                    "url": "https://x.com/wealthcodedna",
                    "showIcon": true,
                    "icon": "twitter",
                    "iconPosition": "left",
                    "style": "secondary",
                    "elementId": ""
                },
                {
                    "type": "Link",
                    "label": "YouTube",
                    "altText": "YouTube",
                    "url": "https://www.youtube.com/@wealthdna-code",
                    "showIcon": true,
                    "icon": "youtube",
                    "iconPosition": "left",
                    "style": "secondary",
                    "elementId": ""
                },
                {
                    "type": "Link",
                    "label": "LinkedIn",
                    "altText": "LinkedIn",
                    "url": "https://www.linkedin.com/in/teguh-mulyantoro-968061341/",
                    "showIcon": true,
                    "icon": "linkedin",
                    "iconPosition": "left",
                    "style": "secondary",
                    "elementId": ""
                }
            ],
            "labelStyle": "primary",
            "type": "SubNav"
        }
    ],
    "secondaryLinks": [],
    "variant": "logo-left-primary-nav-centered",
    "colors": "bg-light-fg-dark",
    "type": "Header"
}